dls_optics_core/__init__.py
dls_optics_core/analysis/__init__.py
dls_optics_core/analysis/image.py
dls_optics_core/analysis/peakfitting.py
dls_optics_core/analysis/pencilbeamscan.py
dls_optics_core/analysis/pgmcalibration.py
dls_optics_core/analysis/functions/plane.py
dls_optics_core/beam/__init__.py
dls_optics_core/beam/beam.py
dls_optics_core/beam/image.py
dls_optics_core/beam/polarization.py
dls_optics_core/beam/ray.py
dls_optics_core/components/__init__.py
dls_optics_core/components/beamline.py
dls_optics_core/components/element.py
dls_optics_core/components/ellipsoid_mirror.py
dls_optics_core/components/grating.py
dls_optics_core/components/mirror.py
dls_optics_core/components/paraboloid_mirror.py
dls_optics_core/components/pgm.py
dls_optics_core/components/polarimeter.py
dls_optics_core/components/undulator.py
dls_optics_core/geometry/__init__.py
dls_optics_core/geometry/plane.py
dls_optics_core/geometry/point3d.py
dls_optics_core/geometry/ray3d.py
dls_optics_core/geometry/shapes.py
dls_optics_core/geometry/vector2d.py
dls_optics_core/geometry/vector3d.py
dls_optics_core/io/__init__.py
dls_optics_core/io/nexus.py
dls_optics_core/io/scanlist.py
dls_optics_core/io/scans2d.py
dls_optics_core/io/shadow.py
dls_optics_core/utilities/__init__.py
dls_optics_core/utilities/converter.py
dls_optics_core/visualization/__init__.py
dls_optics_core/visualization/lineplot.py
dls_optics_core/visualization/polarizationvisualizer.py
dls_optics_core/visualization/shadowplot.py
dls_optics_core-0.1.2.dist-info/METADATA
dls_optics_core-0.1.2.dist-info/WHEEL
dls_optics_core-0.1.2.dist-info/top_level.txt
dls_optics_core-0.1.2.dist-info/RECORD
